[
    {
        "id": 1,
        "x1": 128,
        "y1": 45,
        "x2": 226,
        "y2": 156
    },
    {
        "id": 2,
        "x1": 237,
        "y1": 46,
        "x2": 324,
        "y2": 157
    },
    {
        "id": 3,
        "x1": 354,
        "y1": 59,
        "x2": 440,
        "y2": 153
    },
    {
        "id": 4,
        "x1": 201,
        "y1": 257,
        "x2": 244,
        "y2": 297
    },
    {
        "id": 5,
        "x1": 136,
        "y1": 318,
        "x2": 451,
        "y2": 437
    }
]